scqubits/__init__.py
scqubits/py.typed
scqubits/settings.py
scqubits/testing.py
scqubits/version.py
scqubits/core/__init__.py
scqubits/core/central_dispatch.py
scqubits/core/circuit.py
scqubits/core/circuit_input.py
scqubits/core/circuit_noise.py
scqubits/core/circuit_plotting.py
scqubits/core/circuit_routines.py
scqubits/core/circuit_sym_methods.py
scqubits/core/circuit_utils.py
scqubits/core/constants.py
scqubits/core/cos2phi_qubit.py
scqubits/core/descriptors.py
scqubits/core/diag.py
scqubits/core/discretization.py
scqubits/core/flux_qubit.py
scqubits/core/fluxonium.py
scqubits/core/generic_qubit.py
scqubits/core/hilbert_space.py
scqubits/core/namedslots_array.py
scqubits/core/noise.py
scqubits/core/operators.py
scqubits/core/oscillator.py
scqubits/core/param_sweep.py
scqubits/core/qubit_base.py
scqubits/core/spec_lookup.py
scqubits/core/storage.py
scqubits/core/sweeps.py
scqubits/core/symbolic_circuit.py
scqubits/core/symbolic_circuit_graph.py
scqubits/core/transmon.py
scqubits/core/units.py
scqubits/core/zeropi.py
scqubits/core/zeropi_full.py
scqubits/core/qubit_img/Bifluxon.jpg
scqubits/core/qubit_img/Cos2PhiQubit.jpg
scqubits/core/qubit_img/FluxQubit.jpg
scqubits/core/qubit_img/Fluxonium.jpg
scqubits/core/qubit_img/FullZeroPi.jpg
scqubits/core/qubit_img/KerrOscillator.jpg
scqubits/core/qubit_img/Oscillator.jpg
scqubits/core/qubit_img/Snailmon.jpg
scqubits/core/qubit_img/Transmon.jpg
scqubits/core/qubit_img/TunableTransmon.jpg
scqubits/core/qubit_img/ZeroPi.jpg
scqubits/explorer/__init__.py
scqubits/explorer/explorer_panels.py
scqubits/explorer/explorer_settings.py
scqubits/explorer/explorer_widget.py
scqubits/io_utils/__init__.py
scqubits/io_utils/fileio.py
scqubits/io_utils/fileio_backends.py
scqubits/io_utils/fileio_qutip.py
scqubits/io_utils/fileio_serializers.py
scqubits/tests/.coverage
scqubits/tests/__init__.py
scqubits/tests/conftest.py
scqubits/tests/test_centraldispatch.py
scqubits/tests/test_circuit.py
scqubits/tests/test_circuit_plot.py
scqubits-4.3.1.dist-info/licenses/LICENSE
scqubits-4.3.1.dist-info/METADATA
scqubits-4.3.1.dist-info/WHEEL
scqubits-4.3.1.dist-info/top_level.txt
scqubits-4.3.1.dist-info/RECORD
