Metadata-Version: 2.4
Name: scqubits
Version: 4.3.1
Summary: scqubits: superconducting qubits in Python
Author-email: Jens Koch <jens-koch@northwestern.edu>, Peter Groszkowski <piotrekg@gmail.com>
License: BSD 3-Clause License
Project-URL: Homepage, https://scqubits.readthedocs.io
Project-URL: Repository, https://github.com/scqubits/scqubits
Keywords: qubits,superconducting
Classifier: Development Status :: 5 - Production/Stable
Classifier: Intended Audience :: Science/Research
Classifier: License :: OSI Approved :: BSD License
Classifier: Operating System :: MacOS
Classifier: Operating System :: Microsoft :: Windows
Classifier: Operating System :: POSIX
Classifier: Operating System :: Unix
Classifier: Programming Language :: Python
Classifier: Programming Language :: Python :: 3
Classifier: Topic :: Scientific/Engineering
Requires-Python: >=3.9
License-File: LICENSE
Requires-Dist: cycler
Requires-Dist: dill
Requires-Dist: pathos>=0.3.0
Requires-Dist: matplotlib>=3.5.1
Requires-Dist: numpy>=1.14.2
Requires-Dist: pathos>=0.3.0
Requires-Dist: qutip>=4.3.1
Requires-Dist: scipy>=1.5; sys_platform != "darwin"
Requires-Dist: scipy>=1.5; sys_platform == "darwin" and python_version < "3.10"
Requires-Dist: scipy<=1.13.1,>=1.5; sys_platform == "darwin" and python_version >= "3.10"
Requires-Dist: sympy
Requires-Dist: tqdm
Requires-Dist: typing_extensions
Provides-Extra: gui
Requires-Dist: ipywidgets>=7.5; extra == "gui"
Requires-Dist: ipyvuetify; extra == "gui"
Requires-Dist: matplotlib-label-lines>=0.3.6; extra == "gui"
Requires-Dist: h5py>=2.10; extra == "gui"
Provides-Extra: develop
Requires-Dist: pytest; extra == "develop"
Requires-Dist: traitlets; extra == "develop"
Requires-Dist: h5py>=2.10; extra == "develop"
Dynamic: license-file
